kretanje_cijena/__init__.py
kretanje_cijena/__main__.py
kretanje_cijena/base.py
kretanje_cijena/cli.py
kretanje_cijena-0.0.3.dist-info/LICENSE
kretanje_cijena-0.0.3.dist-info/METADATA
kretanje_cijena-0.0.3.dist-info/WHEEL
kretanje_cijena-0.0.3.dist-info/entry_points.txt
kretanje_cijena-0.0.3.dist-info/top_level.txt
kretanje_cijena-0.0.3.dist-info/RECORD
