Metadata-Version: 2.1
Name: kretanje-cijena
Version: 0.0.3
Summary: Preuzimanje i pohranjivanje podataka s kretanje_cijena
Home-page: https://github.com/brahle/kretanje-cijena/
Author: brahle
License-File: LICENSE
Requires-Dist: brds
Requires-Dist: requests
Requires-Dist: types-requests
Provides-Extra: test
Requires-Dist: pytest ; extra == 'test'
Requires-Dist: coverage ; extra == 'test'
Requires-Dist: flake8 ; extra == 'test'
Requires-Dist: black ; extra == 'test'
Requires-Dist: isort ; extra == 'test'
Requires-Dist: pytest-cov ; extra == 'test'
Requires-Dist: codecov ; extra == 'test'
Requires-Dist: mypy ; extra == 'test'
Requires-Dist: gitchangelog ; extra == 'test'
Requires-Dist: mkdocs ; extra == 'test'
